cello/__init__.py
cello/_cello.pypy38-pp73-aarch64-linux-gnu.so
cello/guards.py
cello/validation.py
cello_framework-0.7.0.dist-info/METADATA
cello_framework-0.7.0.dist-info/WHEEL
cello_framework-0.7.0.dist-info/licenses/LICENSE
cello_framework-0.7.0.dist-info/RECORD
