Metadata-Version: 2.4
Name: cello-framework
Version: 0.7.0
Classifier: Development Status :: 4 - Beta
Classifier: Intended Audience :: Developers
Classifier: License :: OSI Approved :: MIT License
Classifier: Programming Language :: Python :: 3
Classifier: Programming Language :: Python :: 3.12
Classifier: Programming Language :: Python :: 3.13
Classifier: Programming Language :: Python :: 3.14
Classifier: Programming Language :: Rust
Classifier: Framework :: AsyncIO
Classifier: Topic :: Internet :: WWW/HTTP :: HTTP Servers
Requires-Dist: pytest>=7.0 ; extra == 'dev'
Requires-Dist: requests>=2.28 ; extra == 'dev'
Requires-Dist: websockets>=11.0 ; extra == 'dev'
Requires-Dist: aiohttp>=3.8 ; extra == 'dev'
Requires-Dist: ruff>=0.1.0 ; extra == 'dev'
Provides-Extra: dev
License-File: LICENSE
Summary: Ultra-fast Rust-powered Python async web framework
Keywords: web,framework,async,rust,fast,http,websocket
Author: Jagadeesh Katla
License: MIT
Requires-Python: >=3.12
Project-URL: Documentation, https://github.com/jagadeesh32/cello#readme
Project-URL: Homepage, https://github.com/jagadeesh32/cello
Project-URL: Repository, https://github.com/jagadeesh32/cello
